vutils/testing/__init__.py
vutils/testing/__init__.pyi
vutils/testing/mock.py
vutils/testing/py.typed
vutils/testing/testcase.py
vutils/testing/utils.py
vutils/testing/version.py
vutils_testing-2.0.3.dist-info/LICENSE
vutils_testing-2.0.3.dist-info/METADATA
vutils_testing-2.0.3.dist-info/WHEEL
vutils_testing-2.0.3.dist-info/top_level.txt
vutils_testing-2.0.3.dist-info/RECORD
