Metadata-Version: 2.1
Name: vutils-testing
Version: 2.0.3
Summary: Auxiliary library for writing tests
Home-page: https://github.com/i386x/vutils-testing
Author: Jiří Kučera
Author-email: sanczes@gmail.com
License: MIT
Project-URL: Bug Reports, https://github.com/i386x/vutils-testing/issues
Project-URL: Source, https://github.com/i386x/vutils-testing
Keywords: testing,mocking,unit testing
Platform: any
Classifier: Development Status :: 5 - Production/Stable
Classifier: Intended Audience :: Developers
Classifier: Intended Audience :: Information Technology
Classifier: License :: OSI Approved :: MIT License
Classifier: Operating System :: OS Independent
Classifier: Programming Language :: Python
Classifier: Programming Language :: Python :: 3
Classifier: Programming Language :: Python :: 3 :: Only
Classifier: Topic :: Software Development
Classifier: Topic :: Software Development :: Libraries
Classifier: Topic :: Software Development :: Libraries :: Python Modules
Classifier: Topic :: Software Development :: Testing
Classifier: Topic :: Software Development :: Testing :: Mocking
Classifier: Topic :: Software Development :: Testing :: Unit
Classifier: Topic :: Utilities
Requires-Python: <4,>=3.8
License-File: LICENSE
Provides-Extra: dev
Requires-Dist: tox; extra == "dev"
Provides-Extra: test
Requires-Dist: tox; extra == "test"
